README.md
setup.py
tensorplane/__init__.py
tensorplane/test.py
tensorplane.egg-info/PKG-INFO
tensorplane.egg-info/SOURCES.txt
tensorplane.egg-info/dependency_links.txt
tensorplane.egg-info/requires.txt
tensorplane.egg-info/top_level.txt
tensorplane/core/__init__.py
tensorplane/core/data.py
tensorplane/core/lib/__init__.py
tensorplane/core/lib/attrs.py
tensorplane/core/lib/backend.py
tensorplane/core/lib/engine.py
tensorplane/core/lib/index.py
tensorplane/core/lib/utils.py
tensorplane/tests/__init__.py
tensorplane/tests/test_dataset.py
tensorplane/tests/utils.py